biochemHH/GBparser.py
biochemHH/Homolog.py
biochemHH/StructureHH.py
biochemHH/__init__.py
biochemHH/example_input/Oligo_list_0.csv
biochemHH/example_input/Plasmid_list_0.csv
biochemHH/example_input/fasta_example.fasta
biochemHH/example_input/name_definition.csv
biochemHH/example_input/pUC19.gb
biochemHH/example_input/pUCv2-cat.gb
biochemHH/example_input/pUCv2.gb
biochemHH/example_input/structures_2025-12-29-17-10-3/2PYL.C.cif
biochemHH/example_input/structures_2025-12-29-17-10-3/5OMF.A.cif
biochemHH/example_input/structures_2025-12-29-17-10-3/sequence_alignment_2025-12-29-17-10-3.fasta
biochemHH/example_input/structures_2025-12-29-17-10-3/transformation_matrices_2025-12-29-17-10-3.json
biochemHH/example_script/examples_Cloning_(advanced).py
biochemHH/example_script/examples_Cloning_(batch-mode).py
biochemHH/example_script/examples_DNA.py
biochemHH/example_script/examples_Homolog.py
biochemHH/example_script/examples_PDB(CIF)_editing.py
biochemHH/example_script/examples_Protein_analyses.py
biochemHH/example_script/playground.py
biochemhh-0.0.2.dist-info/licenses/LICENSE
biochemhh-0.0.2.dist-info/METADATA
biochemhh-0.0.2.dist-info/WHEEL
biochemhh-0.0.2.dist-info/top_level.txt
biochemhh-0.0.2.dist-info/RECORD
