Metadata-Version: 2.4
Name: biochemHH
Version: 0.0.2
Summary: Biochemistry & molecular biology helper tools
Author: Otter Brown
Author-email: 
License: GPL-2.0-only
Keywords: biochemistry molecular biology bioinformatics
Classifier: License :: OSI Approved :: GNU General Public License v2 (GPLv2)
Classifier: Programming Language :: Python :: 3
Classifier: Operating System :: OS Independent
Requires-Python: >=3.8
License-File: LICENSE
Requires-Dist: biopython
Requires-Dist: numpy
Requires-Dist: scipy
Requires-Dist: matplotlib
Requires-Dist: pandas
Requires-Dist: primer3-py
Requires-Dist: pillow
Requires-Dist: chardet
Dynamic: author
Dynamic: classifier
Dynamic: description
Dynamic: description-content-type
Dynamic: keywords
Dynamic: license
Dynamic: license-file
Dynamic: requires-dist
Dynamic: requires-python
Dynamic: summary
